chainsettle_sdk/__init__.py
chainsettle_sdk/chainsettle.py
chainsettle_sdk/config.py
chainsettle_sdk/utils/error_handler.py
chainsettle_sdk/utils/helpers.py
chainsettle_sdk-0.1.4.dist-info/METADATA
chainsettle_sdk-0.1.4.dist-info/WHEEL
chainsettle_sdk-0.1.4.dist-info/top_level.txt
chainsettle_sdk-0.1.4.dist-info/RECORD
