Metadata-Version: 2.4
Name: chainsettle-sdk
Version: 0.1.4
Summary: SDK for ChainSettle API integrations.
Author-email: Brandyn Hamilton <brandynham1120@gmail.com>
License-Expression: MIT
Requires-Python: >=3.7
Requires-Dist: web3
Requires-Dist: requests
Requires-Dist: python-dotenv
Requires-Dist: pydantic-settings>=2.0.3
Provides-Extra: dev
Requires-Dist: build; extra == "dev"
Requires-Dist: twine; extra == "dev"
